CONTRIBUTING.md
chatsky/__init__.py
chatsky/__rebuild_pydantic_models__.py
chatsky/conditions/__init__.py
chatsky/conditions/llm.py
chatsky/conditions/service.py
chatsky/conditions/slots.py
chatsky/conditions/standard.py
chatsky/config/README.md
chatsky/config/superset_dashboard/charts/Current_topic_slot_bar_chart_4.yaml
chatsky/config/superset_dashboard/charts/Current_topic_time_series_bar_chart_2.yaml
chatsky/config/superset_dashboard/charts/Flow_visit_ratio_monitor_13.yaml
chatsky/config/superset_dashboard/charts/Node_Visits_7.yaml
chatsky/config/superset_dashboard/charts/Node_counts_3.yaml
chatsky/config/superset_dashboard/charts/Node_visit_ratio_monitor_8.yaml
chatsky/config/superset_dashboard/charts/Node_visits_ratio_6.yaml
chatsky/config/superset_dashboard/charts/Node_visits_sunburst_5.yaml
chatsky/config/superset_dashboard/charts/Rating_slot_line_chart_1.yaml
chatsky/config/superset_dashboard/charts/Requests_17.yaml
chatsky/config/superset_dashboard/charts/Responses_16.yaml
chatsky/config/superset_dashboard/charts/Service_load_users_9.yaml
chatsky/config/superset_dashboard/charts/Table_14.yaml
chatsky/config/superset_dashboard/charts/Terminal_labels_15.yaml
chatsky/config/superset_dashboard/charts/Transition_counts_12.yaml
chatsky/config/superset_dashboard/charts/Transition_layout_10.yaml
chatsky/config/superset_dashboard/charts/Transition_ratio_chord_11.yaml
chatsky/config/superset_dashboard/dashboards/chatsky_statistics_dashboard_1.yaml
chatsky/config/superset_dashboard/databases/chatsky_database.yaml
chatsky/config/superset_dashboard/datasets/chatsky_database/chatsky_final_nodes.yaml
chatsky/config/superset_dashboard/datasets/chatsky_database/chatsky_node_stats.yaml
chatsky/config/superset_dashboard/datasets/chatsky_database/chatsky_stats.yaml
chatsky/config/superset_dashboard/metadata.yaml
chatsky/context_storages/__init__.py
chatsky/context_storages/database.py
chatsky/context_storages/file.py
chatsky/context_storages/memory.py
chatsky-0.10.0.dist-info/LICENSE
chatsky-0.10.0.dist-info/METADATA
chatsky-0.10.0.dist-info/WHEEL
chatsky-0.10.0.dist-info/entry_points.txt
chatsky-0.10.0.dist-info/RECORD
